[{"id": 501, "user_id": 501, "name": "Sultan Asia", "src": "/img/circle_cut/circle_cut_blank.png", "sample": "/img/sampleworks/Sultan_Asia.jpg", "isSaturday": 1, "isSunday": 0, "SellsArtbook": 0, "SellsCD": 0, "SellsComic": 0, "SellsGameAnalog": 0, "SellsGameDigital": 0, "SellsGoods": 1, "SellsLiveCommision": 0, "SellsNovel": 0, "SellsPhotobook": 0, "booth_number": "Q-03a (SUN)", "fandom": "Utaite, Kpop, Kimetsu no Yaiba, Identity V", "rating": "General Audience (GA)", "circle_twitter": "https://twitter.com/mirushi04?s=09", "circle_instagram": "https://www.instagram.com/mikyungie/", "circle_facebook": "-"}, {"id": 502, "user_id": 502, "name": "Ranime rantoys", "src": "/img/circle_cut/circle_cut_blank.png", "sample": "-", "isSaturday": 1, "isSunday": 1, "SellsArtbook": 0, "SellsCD": 0, "SellsComic": 0, "SellsGameAnalog": 0, "SellsGameDigital": 0, "SellsGoods": 1, "SellsLiveCommision": 0, "SellsNovel": 0, "SellsPhotobook": 0, "booth_number": "Q-03b", "fandom": "Sao , tokyo ghoul, kimetsu no yaiba", "rating": "GA", "circle_twitter": "-", "circle_instagram": "-", "circle_facebook": "-"}, {"id": 503, "user_id": 503, "name": "Kutunggu SSR Wosoalao", "src": "/img/circle_cut/kutunggussrwosoalao.png", "sample": "/img/sampleworks/Kutunggu_SSR_Wosoalao.jpg", "isSaturday": 1, "isSunday": 1, "SellsArtbook": 1, "SellsCD": 0, "SellsComic": 1, "SellsGameAnalog": 0, "SellsGameDigital": 0, "SellsGoods": 1, "SellsLiveCommision": 1, "SellsNovel": 0, "SellsPhotobook": 0, "booth_number": "Q-04ab", "fandom": "Idolm@ster, Kimetsu no Yaiba, A3, Fire Force, JOJO, Mononoke, Hanano-kun, Tiger and Bunny, Double Decker, Original, Arslan Senki", "rating": "PG", "circle_twitter": "https://twitter.com/wosoalao", "circle_instagram": "-", "circle_facebook": "-"}, {"id": 504, "user_id": 504, "name": "\"Our Booth Kita\"", "src": "/img/circle_cut/ourboothkita.jpg", "sample": "-", "isSaturday": 1, "isSunday": 0, "SellsArtbook": 0, "SellsCD": 0, "SellsComic": 0, "SellsGameAnalog": 0, "SellsGameDigital": 0, "SellsGoods": 1, "SellsLiveCommision": 1, "SellsNovel": 0, "SellsPhotobook": 0, "booth_number": "Q-05a (SAT)", "fandom": "Kimetsu no Yaiba,Danganronpa,My Hero Academia,DanPlan", "rating": "General Audience (GA)", "circle_twitter": "-", "circle_instagram": "-", "circle_facebook": "-"}, {"id": 505, "user_id": 505, "name": "M@GER", "src": "/img/circle_cut/mager.png", "sample": "-", "isSaturday": 0, "isSunday": 1, "SellsArtbook": 0, "SellsCD": 0, "SellsComic": 1, "SellsGameAnalog": 0, "SellsGameDigital": 0, "SellsGoods": 1, "SellsLiveCommision": 1, "SellsNovel": 0, "SellsPhotobook": 0, "booth_number": "Q-05a (SUN)", "fandom": "THE iDOLM@STER Series (765Pro All Stars, Cinderella Girls, Million Live, Shiny Colors, SideM)", "rating": "PG", "circle_twitter": "-", "circle_instagram": "-", "circle_facebook": "https://www.facebook.com/Chiko-744882742380933/?ref=bookmarks"}, {"id": 506, "user_id": 506, "name": "Retjeh Ass-emble", "src": "/img/circle_cut/retjeh_assemble.jpg", "sample": "-", "isSaturday": 1, "isSunday": 1, "SellsArtbook": 0, "SellsCD": 0, "SellsComic": 0, "SellsGameAnalog": 0, "SellsGameDigital": 0, "SellsGoods": 1, "SellsLiveCommision": 0, "SellsNovel": 0, "SellsPhotobook": 0, "booth_number": "Q-05b", "fandom": "Kimetsu no Yaiba, Handmade Craft, Houseki no Kuni, Cardcaptor Sakura", "rating": "GA", "circle_twitter": "-", "circle_instagram": "https://www.instagram.com/celsdyr_/", "circle_facebook": "-"}, {"id": 507, "user_id": 507, "name": "lumirouso", "src": "/img/circle_cut/lumirouso.png", "sample": "/img/sampleworks/lumirouso.png", "isSaturday": 1, "isSunday": 1, "SellsArtbook": 0, "SellsCD": 0, "SellsComic": 0, "SellsGameAnalog": 0, "SellsGameDigital": 0, "SellsGoods": 1, "SellsLiveCommision": 0, "SellsNovel": 0, "SellsPhotobook": 0, "booth_number": "Q-06a", "fandom": "Kimetsu no Yaiba, Mobile Legends, Original Content", "rating": "General Audience (GA)", "circle_twitter": "-", "circle_instagram": "https://instagram.com/lumirouso", "circle_facebook": "-"}, {"id": 508, "user_id": 508, "name": "Truck menuju Isekai", "src": "/img/circle_cut/truckmenujuisekai.jpg", "sample": "/img/sampleworks/Truck_menuju_Isekai.png", "isSaturday": 1, "isSunday": 1, "SellsArtbook": 0, "SellsCD": 0, "SellsComic": 0, "SellsGameAnalog": 0, "SellsGameDigital": 0, "SellsGoods": 1, "SellsLiveCommision": 1, "SellsNovel": 0, "SellsPhotobook": 0, "booth_number": "Q-06b", "fandom": "Identity V, Kimetsu no Yaiba, Ensemble Stars, Haikyuu, Hypnosis Mic, Hanako,", "rating": "Parental Guidance (PG)", "circle_twitter": "-", "circle_instagram": "https://instagram.com/trucksamaa/", "circle_facebook": "-"}, {"id": 509, "user_id": 509, "name": "Akinoscent", "src": "/img/circle_cut/akinocent.jpg", "sample": "-", "isSaturday": 1, "isSunday": 1, "SellsArtbook": 0, "SellsCD": 0, "SellsComic": 0, "SellsGameAnalog": 0, "SellsGameDigital": 0, "SellsGoods": 1, "SellsLiveCommision": 1, "SellsNovel": 0, "SellsPhotobook": 0, "booth_number": "Q-07a", "fandom": "Kimetsu no Yaiba, Identity V, Beastars", "rating": "PG", "circle_twitter": "https://twitter.com/akinoscent", "circle_instagram": "https://www.instagram.com/akinoscent/", "circle_facebook": "https://www.facebook.com/akinoscent/"}, {"id": 510, "user_id": 510, "name": "Nekotin", "src": "/img/circle_cut/nekotin.jpg", "sample": "-", "isSaturday": 1, "isSunday": 1, "SellsArtbook": 0, "SellsCD": 0, "SellsComic": 0, "SellsGameAnalog": 0, "SellsGameDigital": 0, "SellsGoods": 1, "SellsLiveCommision": 0, "SellsNovel": 0, "SellsPhotobook": 0, "booth_number": "Q-07b", "fandom": "Kimetsu no yaiba, Identity V, Given, Utaite, Touken ranbu, Ghibli, Mo Xiang Tong Xiu, Original, Jibaku Sh\u014dnen Hanako-kun, Kpop, Pokemon, Vocaloid, Tenki No Ko", "rating": "General Audience (GA)", "circle_twitter": "-", "circle_instagram": "https://www.instagram.com/nekotins/", "circle_facebook": "-"}, {"id": 511, "user_id": 511, "name": "273//project", "src": "/img/circle_cut/273.jpg", "sample": "-", "isSaturday": 1, "isSunday": 1, "SellsArtbook": 0, "SellsCD": 0, "SellsComic": 0, "SellsGameAnalog": 0, "SellsGameDigital": 0, "SellsGoods": 1, "SellsLiveCommision": 1, "SellsNovel": 0, "SellsPhotobook": 0, "booth_number": "Q-08a", "fandom": "Kimetsu no Yaiba, Jojo's Bizzare Adventure, Puella Magi Madoka Magica, VTuber", "rating": "PG", "circle_twitter": "https://twitter.com/273project", "circle_instagram": "https://www.instagram.com/273project/", "circle_facebook": "-"}, {"id": 512, "user_id": 512, "name": "277353", "src": "/img/circle_cut/277353.jpg", "sample": "-", "isSaturday": 1, "isSunday": 1, "SellsArtbook": 1, "SellsCD": 0, "SellsComic": 0, "SellsGameAnalog": 0, "SellsGameDigital": 0, "SellsGoods": 1, "SellsLiveCommision": 1, "SellsNovel": 0, "SellsPhotobook": 0, "booth_number": "Q-08b", "fandom": "Kimetsu no yaiba, nintendo, furry, identity v", "rating": "GA", "circle_twitter": "https://twitter.com/kimchireo?lang=en", "circle_instagram": "https://www.instagram.com/kimchireo/", "circle_facebook": "-"}, {"id": 513, "user_id": 513, "name": "Lazy Cosign", "src": "/img/circle_cut/lazycosign.jpg", "sample": "-", "isSaturday": 1, "isSunday": 1, "SellsArtbook": 1, "SellsCD": 0, "SellsComic": 0, "SellsGameAnalog": 0, "SellsGameDigital": 0, "SellsGoods": 1, "SellsLiveCommision": 0, "SellsNovel": 0, "SellsPhotobook": 0, "booth_number": "Q-09a", "fandom": "Kimetsu no Yaiba, One Punch Man, Jojo Bizzare, Mystic Messenger, Detective Conan, Original dan lain lain", "rating": "GA", "circle_twitter": "-", "circle_instagram": "-", "circle_facebook": "-"}, {"id": 514, "user_id": 514, "name": "Otter Kanyut :3", "src": "/img/circle_cut/otterkanyut.jpg", "sample": "-", "isSaturday": 1, "isSunday": 1, "SellsArtbook": 1, "SellsCD": 0, "SellsComic": 0, "SellsGameAnalog": 0, "SellsGameDigital": 0, "SellsGoods": 1, "SellsLiveCommision": 1, "SellsNovel": 0, "SellsPhotobook": 0, "booth_number": "Q-09b", "fandom": "Kimetsu No Yaiba, Original, Live Commision, Love Live!, Keyakizaka46, Utaite, Identity V, FGO, Jojo, Pokemon, etc", "rating": "General Audience (GA)", "circle_twitter": "https://twitter.com/kizaceo_", "circle_instagram": "https://www.instagram.com/kizaceo_", "circle_facebook": "https://www.facebook.com/kizaceo"}, {"id": 515, "user_id": 515, "name": "Kochenk Barbar", "src": "/img/circle_cut/kochenkbarbar.jpg", "sample": "-", "isSaturday": 1, "isSunday": 1, "SellsArtbook": 0, "SellsCD": 0, "SellsComic": 0, "SellsGameAnalog": 0, "SellsGameDigital": 0, "SellsGoods": 1, "SellsLiveCommision": 0, "SellsNovel": 0, "SellsPhotobook": 0, "booth_number": "Q-10a", "fandom": "Kimetsu no Yaiba, Promised Neverland, Harry Potter", "rating": "GA", "circle_twitter": "-", "circle_instagram": "https://instagram.com//missilemeerkat", "circle_facebook": "-"}, {"id": 516, "user_id": 516, "name": "Pt Ya Sudahlah", "src": "/img/circle_cut/pt_yasudahlah.jpg", "sample": "-", "isSaturday": 1, "isSunday": 1, "SellsArtbook": 0, "SellsCD": 0, "SellsComic": 0, "SellsGameAnalog": 0, "SellsGameDigital": 0, "SellsGoods": 1, "SellsLiveCommision": 0, "SellsNovel": 0, "SellsPhotobook": 0, "booth_number": "Q-10b", "fandom": "Kimetsu no Yaiba, Seventeen, Fire Force, Boku no Hero Academia, Homkai Impact 3", "rating": "PG", "circle_twitter": "-", "circle_instagram": "-", "circle_facebook": "-"}, {"id": 517, "user_id": 517, "name": "IDK!?", "src": "/img/circle_cut/idk.jpg", "sample": "-", "isSaturday": 1, "isSunday": 1, "SellsArtbook": 1, "SellsCD": 0, "SellsComic": 0, "SellsGameAnalog": 0, "SellsGameDigital": 0, "SellsGoods": 1, "SellsLiveCommision": 1, "SellsNovel": 0, "SellsPhotobook": 0, "booth_number": "Q-11a", "fandom": "Kimetsu no Yaiba, The promised Neverland, over the garden suikoden, final fantasy, haikyuu, ghibli, Boku no hero academia, haikyuu, life is strange, gran blue fantasy", "rating": "GA", "circle_twitter": "-", "circle_instagram": "https://instagram.com/idk.cmfr", "circle_facebook": "-"}, {"id": 518, "user_id": 518, "name": "Tamago Design", "src": "/img/circle_cut/tamagodesign.jpg", "sample": "-", "isSaturday": 1, "isSunday": 1, "SellsArtbook": 0, "SellsCD": 0, "SellsComic": 0, "SellsGameAnalog": 0, "SellsGameDigital": 0, "SellsGoods": 1, "SellsLiveCommision": 0, "SellsNovel": 0, "SellsPhotobook": 0, "booth_number": "Q-11b", "fandom": "Kimetsu no Yaiba, Touken Ranbu, Fairy Tail, Idolish7, Yu-gi-oh", "rating": "GA", "circle_twitter": "https://twitter.com/hazurin_akita", "circle_instagram": "https://www.instagram.com/tamago.design/", "circle_facebook": "https://www.facebook.com/tamagomerch/"}, {"id": 519, "user_id": 519, "name": "CAPCIPCUP", "src": "/img/circle_cut/capcipcup.jpg", "sample": "-", "isSaturday": 1, "isSunday": 1, "SellsArtbook": 1, "SellsCD": 0, "SellsComic": 1, "SellsGameAnalog": 0, "SellsGameDigital": 0, "SellsGoods": 1, "SellsLiveCommision": 1, "SellsNovel": 0, "SellsPhotobook": 0, "booth_number": "Q-12ab/Q-13ab", "fandom": "Kimetsu no Yaiba, boku no hero academia, Ghibli, CCS, Sailor moon", "rating": "GA", "circle_twitter": "https://twitter.com/Loredanzo", "circle_instagram": "https://www.instagram.com/loredanzo/", "circle_facebook": "-"}, {"id": 520, "user_id": 520, "name": "Omega", "src": "/img/circle_cut/omega.jpg", "sample": "/img/sampleworks/Omega.jpg", "isSaturday": 1, "isSunday": 1, "SellsArtbook": 1, "SellsCD": 0, "SellsComic": 0, "SellsGameAnalog": 0, "SellsGameDigital": 0, "SellsGoods": 1, "SellsLiveCommision": 1, "SellsNovel": 0, "SellsPhotobook": 0, "booth_number": "Q-14a", "fandom": "KnY, BnHA, idolM@ster!, Dr.Stone, FGO, K-ON!, Fairy Gone, Day6, GoT, Harry Potter, Overwatch, Original", "rating": "Parental Guidance (PG)", "circle_twitter": "-", "circle_instagram": "https://www.instagram.com/siml_rif/", "circle_facebook": "-"}, {"id": 521, "user_id": 521, "name": "#SickSoul", "src": "/img/circle_cut/sicksoul.jpg", "sample": "/img/sampleworks/#SickSoul.jpeg", "isSaturday": 1, "isSunday": 1, "SellsArtbook": 0, "SellsCD": 0, "SellsComic": 0, "SellsGameAnalog": 0, "SellsGameDigital": 0, "SellsGoods": 1, "SellsLiveCommision": 1, "SellsNovel": 0, "SellsPhotobook": 0, "booth_number": "Q-14b", "fandom": "KnY, TPN, FGO, Beastars, Banana Fish, Given, IDV, original art", "rating": "Parental Guidance (PG)", "circle_twitter": "-", "circle_instagram": "https://www.instagram.com/sicksoul.id/?hl=en", "circle_facebook": "-"}, {"id": 522, "user_id": 522, "name": "Hidup Mati", "src": "/img/circle_cut/hidupmati.png", "sample": "/img/sampleworks/Hidup_Mati.jpg", "isSaturday": 1, "isSunday": 0, "SellsArtbook": 0, "SellsCD": 0, "SellsComic": 0, "SellsGameAnalog": 0, "SellsGameDigital": 0, "SellsGoods": 1, "SellsLiveCommision": 0, "SellsNovel": 0, "SellsPhotobook": 0, "booth_number": "Q-15a (SAT)", "fandom": "Kimetsu no Yaiba", "rating": "Parental Guidance (PG)", "circle_twitter": "-", "circle_instagram": "-", "circle_facebook": "https://facebook.com/ahokitsune"}, {"id": 523, "user_id": 523, "name": "The new B", "src": "/img/circle_cut/thenewb.png", "sample": "-", "isSaturday": 1, "isSunday": 0, "SellsArtbook": 0, "SellsCD": 0, "SellsComic": 0, "SellsGameAnalog": 0, "SellsGameDigital": 0, "SellsGoods": 1, "SellsLiveCommision": 0, "SellsNovel": 0, "SellsPhotobook": 0, "booth_number": "Q-15a (SUN)", "fandom": "KnY, Haikyuu, original", "rating": "GA", "circle_twitter": "-", "circle_instagram": "Https://facebook.com/kyuto_hans/", "circle_facebook": "Https://facebook.com/kyuto hans/"}, {"id": 524, "user_id": 524, "name": "UwU", "src": "/img/circle_cut/uwu.jpeg", "sample": "-", "isSaturday": 1, "isSunday": 0, "SellsArtbook": 0, "SellsCD": 0, "SellsComic": 0, "SellsGameAnalog": 0, "SellsGameDigital": 0, "SellsGoods": 1, "SellsLiveCommision": 0, "SellsNovel": 0, "SellsPhotobook": 0, "booth_number": "Q-15b (SAT)", "fandom": "Kimetsu no yaiba, Bangdream! girls band party, boku no hero academia, marvel, hypnosis mic", "rating": "GA", "circle_twitter": "-", "circle_instagram": "instagram.com/chocomaltmochi", "circle_facebook": "-"}, {"id": 525, "user_id": 525, "name": "Osa and friends", "src": "/img/circle_cut/osa_n_friend.png", "sample": "-", "isSaturday": 0, "isSunday": 1, "SellsArtbook": 1, "SellsCD": 0, "SellsComic": 1, "SellsGameAnalog": 0, "SellsGameDigital": 0, "SellsGoods": 1, "SellsLiveCommision": 0, "SellsNovel": 0, "SellsPhotobook": 0, "booth_number": "Q-15b (SUN)", "fandom": "Kimetsu no Yaiba", "rating": "PG", "circle_twitter": "https://twitter.com/_ayuuka", "circle_instagram": "-", "circle_facebook": "-"}, {"id": 526, "user_id": 526, "name": "Chiilea", "src": "/img/circle_cut/chiilea.jpg", "sample": "-", "isSaturday": 1, "isSunday": 0, "SellsArtbook": 0, "SellsCD": 0, "SellsComic": 0, "SellsGameAnalog": 0, "SellsGameDigital": 0, "SellsGoods": 1, "SellsLiveCommision": 0, "SellsNovel": 0, "SellsPhotobook": 0, "booth_number": "Q-16a (SAT)", "fandom": "Kimetsu no Yaiba, Fate Grand Order, Promised neverland, BTS, overwatch", "rating": "GA", "circle_twitter": "-", "circle_instagram": "https://instagram.com/chiilea", "circle_facebook": "-"}, {"id": 527, "user_id": 527, "name": "AS nano nano", "src": "/img/circle_cut/as_nano.jpg", "sample": "-", "isSaturday": 0, "isSunday": 1, "SellsArtbook": 0, "SellsCD": 0, "SellsComic": 0, "SellsGameAnalog": 0, "SellsGameDigital": 0, "SellsGoods": 1, "SellsLiveCommision": 0, "SellsNovel": 0, "SellsPhotobook": 0, "booth_number": "Q-16a (SUN)", "fandom": "Kimetsu no Yaiba, Boku no hero, Fate Grand Order, BTS,X1", "rating": "GA", "circle_twitter": "-", "circle_instagram": "-", "circle_facebook": "-"}, {"id": 528, "user_id": 528, "name": "Epic three", "src": "/img/circle_cut/circle_cut_blank.png", "sample": "/img/sampleworks/Epic_three.jpg", "isSaturday": 1, "isSunday": 0, "SellsArtbook": 0, "SellsCD": 0, "SellsComic": 0, "SellsGameAnalog": 0, "SellsGameDigital": 0, "SellsGoods": 1, "SellsLiveCommision": 0, "SellsNovel": 0, "SellsPhotobook": 0, "booth_number": "Q-16b (SAT)", "fandom": "Kimetsu no yaiba, houseki no kuni, bts,  touhou, bts,boku no hero academia, bungou stray dogs,", "rating": "Parental Guidance (PG)", "circle_twitter": "https://mobile.twitter.com/bungaadef", "circle_instagram": "-", "circle_facebook": "-"}, {"id": 529, "user_id": 529, "name": "META STUDIO", "src": "/img/circle_cut/metastudio.jpg", "sample": "-", "isSaturday": 0, "isSunday": 1, "SellsArtbook": 1, "SellsCD": 0, "SellsComic": 1, "SellsGameAnalog": 0, "SellsGameDigital": 0, "SellsGoods": 1, "SellsLiveCommision": 0, "SellsNovel": 0, "SellsPhotobook": 0, "booth_number": "Q-16b (SUN)", "fandom": "KImetsu no Yaiba, BTS, Yu Gi Oh,", "rating": "GA", "circle_twitter": "-", "circle_instagram": "-", "circle_facebook": "-"}, {"id": 530, "user_id": 530, "name": "witless", "src": "/img/circle_cut/witless.jpg", "sample": "-", "isSaturday": 1, "isSunday": 0, "SellsArtbook": 0, "SellsCD": 0, "SellsComic": 0, "SellsGameAnalog": 0, "SellsGameDigital": 0, "SellsGoods": 1, "SellsLiveCommision": 0, "SellsNovel": 0, "SellsPhotobook": 0, "booth_number": "Q-17a (SAT)", "fandom": "Kimetsu no Yaiba, Kpop (BTS, Seventeen), Jojo, Identity V, ORV", "rating": "GA", "circle_twitter": "-", "circle_instagram": "-", "circle_facebook": "https://www.facebook.com/Witless-114311613347206/?modal=admin_todo_tour"}, {"id": 531, "user_id": 531, "name": "Peachy Summer", "src": "/img/circle_cut/peachysummer.png", "sample": "/img/sampleworks/Peachy_Summer.png", "isSaturday": 0, "isSunday": 1, "SellsArtbook": 1, "SellsCD": 0, "SellsComic": 1, "SellsGameAnalog": 0, "SellsGameDigital": 0, "SellsGoods": 1, "SellsLiveCommision": 1, "SellsNovel": 0, "SellsPhotobook": 0, "booth_number": "Q-17a (SUN)", "fandom": "Kimetsu no Yaiba, BanG Dream, Paradox Live, Fate Grand Order, BTS, Original, Card Captor Sakura, Jibaku Shonen Hanako-Kun, Enen no Shobotai, Vocaloid, Sarazanmai", "rating": "General Audience (GA)", "circle_twitter": "-", "circle_instagram": "-", "circle_facebook": "-"}, {"id": 532, "user_id": 532, "name": "Cincau Balado", "src": "/img/circle_cut/cincaubalado.jpg", "sample": "/img/sampleworks/Cincau_Balado.png", "isSaturday": 1, "isSunday": 0, "SellsArtbook": 1, "SellsCD": 0, "SellsComic": 0, "SellsGameAnalog": 0, "SellsGameDigital": 0, "SellsGoods": 1, "SellsLiveCommision": 0, "SellsNovel": 0, "SellsPhotobook": 0, "booth_number": "Q-17b (SAT)", "fandom": "Kimetsu no Yaiba, Promised Neverland, Haikyuu, Ghibli, Promare, BNHA, Vocaloid, BTS, ORI", "rating": "General Audience (GA)", "circle_twitter": "-", "circle_instagram": "https://instagram.com/cincaubld", "circle_facebook": "-"}, {"id": 533, "user_id": 533, "name": "NU-KA!", "src": "/img/circle_cut/nu-ka.png", "sample": "-", "isSaturday": 0, "isSunday": 1, "SellsArtbook": 0, "SellsCD": 0, "SellsComic": 0, "SellsGameAnalog": 0, "SellsGameDigital": 0, "SellsGoods": 1, "SellsLiveCommision": 0, "SellsNovel": 0, "SellsPhotobook": 0, "booth_number": "Q-17b (SUN)", "fandom": "Kimetsu No Yaiba, Haikyuu, Harry Potter, Boku No Hero Academia", "rating": "PG", "circle_twitter": "-", "circle_instagram": "https://www.instagram.com/nuka_soda/?hl=id", "circle_facebook": "https://web.facebook.com/NuKasoda/"}, {"id": 534, "user_id": 534, "name": "Untitled Circle Game", "src": "/img/circle_cut/untitledcirclegame.jpg", "sample": "-", "isSaturday": 1, "isSunday": 1, "SellsArtbook": 1, "SellsCD": 0, "SellsComic": 1, "SellsGameAnalog": 0, "SellsGameDigital": 0, "SellsGoods": 1, "SellsLiveCommision": 1, "SellsNovel": 0, "SellsPhotobook": 0, "booth_number": "Q-18ab", "fandom": "Kimetsu no Yaiba, Original, Granblue Fantasy, Identity V, Idol", "rating": "PG", "circle_twitter": "https://twitter.com/qiiboard", "circle_instagram": "https://www.instagram.com/tsuyashin/", "circle_facebook": "-"}, {"id": 535, "user_id": 535, "name": "Disconnect Nine", "src": "/img/circle_cut/disconnect_nine.jpg", "sample": "-", "isSaturday": 1, "isSunday": 1, "SellsArtbook": 0, "SellsCD": 0, "SellsComic": 0, "SellsGameAnalog": 0, "SellsGameDigital": 0, "SellsGoods": 1, "SellsLiveCommision": 0, "SellsNovel": 0, "SellsPhotobook": 0, "booth_number": "R-01ab", "fandom": "Kimetsu no Yaiba, Pokemon, BTS/BT21, Ghibli, Marvel Cinematic Universe, Fire FOrce, Boku no Hero Academia, Haikyuu, Bungou Stray Dogs", "rating": "GA", "circle_twitter": "https://twitter.com/calcipuff", "circle_instagram": "https://www.instagram.com/calcipuff/", "circle_facebook": "-"}, {"id": 536, "user_id": 536, "name": "Manjuice x Confused", "src": "/img/circle_cut/manjuice.jpg", "sample": "/img/sampleworks/Manjuice_x_Confused.jpg", "isSaturday": 1, "isSunday": 1, "SellsArtbook": 1, "SellsCD": 0, "SellsComic": 1, "SellsGameAnalog": 0, "SellsGameDigital": 0, "SellsGoods": 1, "SellsLiveCommision": 1, "SellsNovel": 0, "SellsPhotobook": 0, "booth_number": "R-02ab/R-03ab", "fandom": "Kimetsu no yaiba, hypnosis mic, idolish7, promare, tsukino pro, identity v, bnha, A3, ARGONAVIS, kingdom hearts, final fantasy, kpop", "rating": "General Audience (GA)", "circle_twitter": "-", "circle_instagram": "-", "circle_facebook": "https://www.facebook.com/manjuice69/"}, {"id": 537, "user_id": 537, "name": "OwOnion", "src": "/img/circle_cut/owonion.jpg", "sample": "/img/sampleworks/OwOnion.jpg", "isSaturday": 1, "isSunday": 1, "SellsArtbook": 1, "SellsCD": 0, "SellsComic": 1, "SellsGameAnalog": 0, "SellsGameDigital": 0, "SellsGoods": 1, "SellsLiveCommision": 1, "SellsNovel": 0, "SellsPhotobook": 0, "booth_number": "R-04ab", "fandom": "KNY, BNHA, Hypmic, MCU, utaite, TPN, Mob Psycho, ID V, Beastars, SU, Hero Shield, KH, We Bare Bear, Deltarune, IB, Furry, MM, Detroit, Hanako-kun, TMNT, AT, FF, Duck Tales, Bt21, Banana Fish", "rating": "General Audience (GA)", "circle_twitter": "-", "circle_instagram": "https://www.instagram.com/owonioncircle/", "circle_facebook": "https://www.facebook.com/owonioncircle/"}, {"id": 538, "user_id": 538, "name": "Sajenomoto", "src": "/img/circle_cut/sajenomoto.jpg", "sample": "/img/sampleworks/Sajenomoto.png", "isSaturday": 1, "isSunday": 1, "SellsArtbook": 0, "SellsCD": 0, "SellsComic": 0, "SellsGameAnalog": 0, "SellsGameDigital": 0, "SellsGoods": 1, "SellsLiveCommision": 0, "SellsNovel": 0, "SellsPhotobook": 0, "booth_number": "R-05ab", "fandom": "Kimetsu no Yaiba, BnHA, BSD, Identity V, etc.", "rating": "Parental Guidance (PG)", "circle_twitter": "-", "circle_instagram": "https://www.instagram.com/sajenomoto/", "circle_facebook": "-"}, {"id": 539, "user_id": 539, "name": "SWK", "src": "/img/circle_cut/swk.jpg", "sample": "-", "isSaturday": 1, "isSunday": 1, "SellsArtbook": 1, "SellsCD": 0, "SellsComic": 0, "SellsGameAnalog": 0, "SellsGameDigital": 0, "SellsGoods": 1, "SellsLiveCommision": 1, "SellsNovel": 0, "SellsPhotobook": 1, "booth_number": "R-06ab", "fandom": "Kimetsu no Yaiba, Boku no Hero Academia, Tenki no Ko, Kimi no Na wa, Girls und Panzer, Final Fantasy, Pokemon, Ghibli", "rating": "PG", "circle_twitter": "-", "circle_instagram": "-", "circle_facebook": "-"}, {"id": 540, "user_id": 540, "name": "Paperplane", "src": "/img/circle_cut/paperplane.jpg", "sample": "-", "isSaturday": 1, "isSunday": 1, "SellsArtbook": 0, "SellsCD": 0, "SellsComic": 0, "SellsGameAnalog": 0, "SellsGameDigital": 0, "SellsGoods": 1, "SellsLiveCommision": 0, "SellsNovel": 0, "SellsPhotobook": 0, "booth_number": "R-07ab", "fandom": "Kimetsu no Yaiba, Fate Grand Order, Hypnosis Mic, Boku no hero Academia, Cardcaptor Sakura", "rating": "GA", "circle_twitter": "-", "circle_instagram": "https://www.instagram.com/marchfolk/?hl=id", "circle_facebook": "-"}, {"id": 541, "user_id": 541, "name": "get out of here", "src": "/img/circle_cut/circle_cut_blank.png", "sample": "-", "isSaturday": 1, "isSunday": 1, "SellsArtbook": 1, "SellsCD": 0, "SellsComic": 0, "SellsGameAnalog": 0, "SellsGameDigital": 0, "SellsGoods": 1, "SellsLiveCommision": 1, "SellsNovel": 0, "SellsPhotobook": 0, "booth_number": "R-08ab", "fandom": "Kimetsu no yaiba, beastars, FGO, akayona, persona 5, daft punk (western music), houseki no kuni, fire emblem, oc", "rating": "General Audience (GA)", "circle_twitter": "https://twitter.com/treinoux", "circle_instagram": "-", "circle_facebook": "-"}, {"id": 542, "user_id": 542, "name": "J-\u30a6\u30a2\u30e9\u30f3", "src": "/img/circle_cut/j-ualan.png", "sample": "/img/sampleworks/J-\u30a6\u30a2\u30e9\u30f3.jpg", "isSaturday": 1, "isSunday": 1, "SellsArtbook": 1, "SellsCD": 0, "SellsComic": 1, "SellsGameAnalog": 0, "SellsGameDigital": 0, "SellsGoods": 1, "SellsLiveCommision": 1, "SellsNovel": 1, "SellsPhotobook": 0, "booth_number": "R-09ab", "fandom": "Kimetsu No Yaiba, Yandere Simulator, Harry Potter, Jibaku Shounen Hanako-kun, BTS, Ateez, Hazbin Hotels, Deltarune, TwoSetViolin, Good Omens", "rating": "General Audience (GA)", "circle_twitter": "-", "circle_instagram": "https://www.instagram.com/jcom78/?hl=en", "circle_facebook": "-"}, {"id": 543, "user_id": 543, "name": "PotatoKinds", "src": "/img/circle_cut/potatokinds.jpg", "sample": "-", "isSaturday": 1, "isSunday": 1, "SellsArtbook": 1, "SellsCD": 0, "SellsComic": 0, "SellsGameAnalog": 0, "SellsGameDigital": 0, "SellsGoods": 1, "SellsLiveCommision": 1, "SellsNovel": 0, "SellsPhotobook": 0, "booth_number": "R-10ab", "fandom": "kimetsu no yaiba, identity v, studio ghibli", "rating": "PG", "circle_twitter": "-", "circle_instagram": "@potatokinds", "circle_facebook": "-"}, {"id": 544, "user_id": 544, "name": "Bucin Culture", "src": "/img/circle_cut/bucinculture.png", "sample": "-", "isSaturday": 1, "isSunday": 1, "SellsArtbook": 1, "SellsCD": 0, "SellsComic": 0, "SellsGameAnalog": 0, "SellsGameDigital": 0, "SellsGoods": 1, "SellsLiveCommision": 0, "SellsNovel": 0, "SellsPhotobook": 0, "booth_number": "R-11ab", "fandom": "Kimetsu no Yaiba, K-pop, Boku no Hero Academia", "rating": "GA", "circle_twitter": "-", "circle_instagram": "-", "circle_facebook": "-"}, {"id": 545, "user_id": 545, "name": "To The Moon and Back", "src": "/img/circle_cut/to_the_moon_and_back.jpg", "sample": "-", "isSaturday": 1, "isSunday": 1, "SellsArtbook": 0, "SellsCD": 0, "SellsComic": 0, "SellsGameAnalog": 0, "SellsGameDigital": 0, "SellsGoods": 1, "SellsLiveCommision": 0, "SellsNovel": 0, "SellsPhotobook": 0, "booth_number": "R-12ab", "fandom": "Kimetsu no Yaiba, Marvel Cinematic Universe, Haikyuu, Boku no Hero Academia, Bungou Stray Dogs, Pokemon, Monster Hunter, Ragnarok, BTS/BT21, Ghibli", "rating": "GA", "circle_twitter": "https://twitter.com/calcipuff", "circle_instagram": "https://www.instagram.com/calcipuff/", "circle_facebook": "-"}, {"id": 546, "user_id": 546, "name": "SideShop.id", "src": "/img/circle_cut/sideshopid.jpg", "sample": "-", "isSaturday": 1, "isSunday": 1, "SellsArtbook": 0, "SellsCD": 0, "SellsComic": 0, "SellsGameAnalog": 0, "SellsGameDigital": 0, "SellsGoods": 1, "SellsLiveCommision": 0, "SellsNovel": 0, "SellsPhotobook": 0, "booth_number": "R-13ab", "fandom": "Kimetsu no Yaiba, Mobile Legends, Adventure Time, Dota2, Others", "rating": "GA", "circle_twitter": "-", "circle_instagram": "https://www.instagram.com/side_shop.id", "circle_facebook": "-"}, {"id": 547, "user_id": 547, "name": "BUTTERSPOON", "src": "/img/circle_cut/butterspoon.jpg", "sample": "/img/sampleworks/BUTTERSPOON.jpg", "isSaturday": 1, "isSunday": 1, "SellsArtbook": 1, "SellsCD": 0, "SellsComic": 0, "SellsGameAnalog": 0, "SellsGameDigital": 0, "SellsGoods": 1, "SellsLiveCommision": 0, "SellsNovel": 0, "SellsPhotobook": 0, "booth_number": "R-14ab", "fandom": "Kimetsu no Yaiba, My Hero Academia, FGO, Fate Grand Order, Marvel", "rating": "General Audience (GA)", "circle_twitter": "https://twitter.com/spoon_butter", "circle_instagram": "https://www.instagram.com/butterspoonofficial/", "circle_facebook": "https://www.facebook.com/butterspoonofficial/"}, {"id": 548, "user_id": 548, "name": "AC3", "src": "/img/circle_cut/ac3.jpg", "sample": "-", "isSaturday": 1, "isSunday": 1, "SellsArtbook": 1, "SellsCD": 0, "SellsComic": 0, "SellsGameAnalog": 0, "SellsGameDigital": 0, "SellsGoods": 1, "SellsLiveCommision": 0, "SellsNovel": 0, "SellsPhotobook": 0, "booth_number": "R-15ab", "fandom": "Kimetsu no Yaiba, Nier Automata, Onmyouji, BTS, Twice, BLACKPINK, THE BOYZ, Utaite,TXT, SEVENTEEN, Original", "rating": "GA", "circle_twitter": "-", "circle_instagram": "https://www.instagram.com/dsatrio99/", "circle_facebook": "https://m.facebook.com/eureka.eureka.3572"}, {"id": 549, "user_id": 549, "name": "carbonara pasta", "src": "/img/circle_cut/carbonarapasta.jpg", "sample": "-", "isSaturday": 1, "isSunday": 1, "SellsArtbook": 1, "SellsCD": 0, "SellsComic": 1, "SellsGameAnalog": 0, "SellsGameDigital": 0, "SellsGoods": 1, "SellsLiveCommision": 1, "SellsNovel": 0, "SellsPhotobook": 0, "booth_number": "R-16ab", "fandom": "Kimetsu no Yaiba, Original, Fate Grand Order, Osomatsu, Detroit, Hataraku, Hetalia dll", "rating": "GA", "circle_twitter": "https://twitter.com/emilycoseya13", "circle_instagram": "https://www.instagram.com/emily_coseyawi2/", "circle_facebook": "https://www.facebook.com/EmilyCoseya13/"}, {"id": 550, "user_id": 550, "name": "Sumpit Udon", "src": "/img/circle_cut/sumpitudon.jpg", "sample": "-", "isSaturday": 1, "isSunday": 1, "SellsArtbook": 0, "SellsCD": 0, "SellsComic": 0, "SellsGameAnalog": 0, "SellsGameDigital": 0, "SellsGoods": 1, "SellsLiveCommision": 0, "SellsNovel": 0, "SellsPhotobook": 0, "booth_number": "R-17a", "fandom": "Musicals,Kimetsu no Yaiba,D.Gray Man,Fate series,Hazbin hotel", "rating": "GA", "circle_twitter": "-", "circle_instagram": "instagram.com/x_kanon_x", "circle_facebook": "-"}]